uonet_request_signer/__init__.py
uonet_request_signer/sign.py
uonet_request_signer-1.0.0.dist-info/LICENSE
uonet_request_signer-1.0.0.dist-info/METADATA
uonet_request_signer-1.0.0.dist-info/WHEEL
uonet_request_signer-1.0.0.dist-info/top_level.txt
uonet_request_signer-1.0.0.dist-info/RECORD
