Metadata-Version: 2.1
Name: uonet-request-signer
Version: 1.0.0
Summary: Uonet+ request signer for Python
Home-page: https://github.com/wulkanowy/uonet-request-signer
Author: Wulkanowy
Author-email: wulkanowyinc@gmail.com
Maintainer: Kacper Ziubryniewicz
Maintainer-email: kapi2289@gmail.com
License: MIT
Platform: UNKNOWN
Classifier: Development Status :: 5 - Production/Stable
Classifier: Intended Audience :: Developers
Classifier: License :: OSI Approved :: MIT License
Classifier: Natural Language :: English
Classifier: Operating System :: OS Independent
Classifier: Programming Language :: Python
Classifier: Topic :: Security :: Cryptography
Classifier: Topic :: Education
Classifier: Topic :: Software Development :: Libraries :: Python Modules
Requires-Dist: pyopenssl
Provides-Extra: testing
Requires-Dist: pytest ; extra == 'testing'
